youcube/__main__.py
youcube/yc_colours.py
youcube/yc_download.py
youcube/yc_logging.py
youcube/yc_magic.py
youcube/yc_spotify.py
youcube/yc_utils.py
youcube/youcube.py
youcube-0.0.0.dist-info/LICENSE.txt
youcube-0.0.0.dist-info/METADATA
youcube-0.0.0.dist-info/WHEEL
youcube-0.0.0.dist-info/top_level.txt
youcube-0.0.0.dist-info/RECORD
