Metadata-Version: 2.1
Name: youcube
Version: 0.0.0
Summary: A server which provides a WebSocket API for YouCube clients
Author: Commandcracker
License: GPL-3.0
Project-URL: Homepage, https://youcube.madefor.cc
Project-URL: Repository, https://github.com/CC-YouCube/server
Project-URL: Documentation, https://youcube.madefor.cc/guides/server/installation/
Keywords: youtube,youcube,computercraft,minecraft
Classifier: Programming Language :: Python :: 3
Classifier: License :: OSI Approved :: GNU General Public License v3 (GPLv3)
Classifier: Natural Language :: English
Classifier: Topic :: Multimedia :: Video
Classifier: Topic :: Multimedia :: Sound/Audio :: Players
Requires-Python: >=3.7
License-File: LICENSE.txt
Requires-Dist: sanic ~=23.12.1
Requires-Dist: yt-dlp ~=2024.4.9
Requires-Dist: ujson ~=5.9.0
Requires-Dist: spotipy ~=2.23.0
